{
  "schema_version": 1,
  "exported_at": "2026-05-06T10:47:15.688Z",
  "app_version": "1.0.0",
  "git_sha": "89f5bb5f9ba3f0095739533ebf48ec17eeb0ae9c",
  "data_source": {
    "type": "trivy",
    "scans_uploaded_total": 1,
    "scans_in_current_graph": [
      {
        "id": "2ac1c607-ae93-4cf6-8361-586145cfcf6d",
        "name": "postgres:15.17-alpine3.22",
        "vuln_count": 25,
        "uploaded_at": "2026-05-06T12:46:29.753182",
        "trivy_created_at": "2026-04-21T11:08:37.890682561Z",
        "trivy_repo_digest": "postgres@sha256:c74f9545833f799e881d29baf61d752016fce684ea0aefc12c959113036fc28f",
        "trivy_artifact_id": "sha256:f6e023547d67188d67afe278fbe817f47d1097f1e71a4dad0ff5d5e04c7ad493",
        "trivy_report_id": "019dafba-5682-7a66-ae67-db7ad25b946f",
        "trivy_version": "0.70.0"
      }
    ],
    "selection_was_implicit": false
  },
  "settings": {
    "granularity": {
      "HOST": "universal",
      "CPE": "HOST",
      "CVE": "CPE",
      "CWE": "CVE",
      "TI": "CWE",
      "VC": "TI"
    },
    "skip_layer_2": true,
    "visibility_hidden": [],
    "cve_merge_mode": "none",
    "environment_filter": {
      "ui": "N",
      "ac": "L"
    },
    "exploit_paths_only_active": false,
    "force_refresh_on_last_rebuild": false,
    "layout": "dagre"
  },
  "metrics": {
    "nodes": 152,
    "edges": 260,
    "unique_cves": 25,
    "trivy_vuln_count": 25,
    "crossings_raw": 1828,
    "crossings_normalized": 0.9411385883565173,
    "crossings_per_edge": 7.030769230769231,
    "drawing_area": 7506959.25,
    "bbox_width": 1707,
    "bbox_height": 4397.75,
    "area_per_node": 49387.88980263158,
    "edge_length_cv": 0.9515096695948458,
    "edge_length_mean": 742.8024691269469,
    "edge_length_std": 706.783731973217,
    "aspect_ratio": 0.38815303280086405,
    "compound_groups_count": 1,
    "compound_largest_group_size": 5,
    "compound_singleton_fraction": 0,
    "compound_size_distribution": {
      "5": 1
    },
    "crossings_mean_angle_deg": 26.930096448800295,
    "crossings_min_angle_deg": 0.2991416177290604,
    "crossings_right_angle_ratio": 0.16356673960612692,
    "crossings_top_pair_share": 0.8036105032822757,
    "crossings_top_pair_label": "ENABLES×ENABLES",
    "crossings_type_pair_distribution": {
      "ENABLES×HAS_VULN": 92,
      "HAS_IMPACT×HAS_VULN": 2,
      "HAS_VULN×LEADS_TO": 1,
      "ENABLES×LEADS_TO": 264,
      "ENABLES×ENABLES": 1469
    },
    "stress_per_pair": 2144492.086348699,
    "stress_per_pair_normalized_edge": 7.468484233081299,
    "stress_per_pair_normalized_diagonal": 16.712441917651788,
    "stress_per_pair_normalized_area": 15.141865088665831,
    "stress_unreachable_pairs": 8449,
    "stress_reachable_pairs": 2876,
    "bridge_edge_proportion": 0,
    "mean_contraction_depth": 0,
    "bridge_edge_count": 0,
    "bridge_chain_length_distribution": {},
    "mean_ecr_weighted": 0,
    "ecr_compounds_count": 0,
    "ecr_per_compound": [],
    "acr_cve_prereqs": 0.2,
    "acr_cve_outcomes": 0.24,
    "acr_cve_node_count": 25
  }
}
